[{"quarter":2,"week":38,"day":4,"date":1,"ad":"2020-09-17","bs":"01.06.2077","tithi":29,"nsYear":1140,"nsMonth":21,"chandrama":21,"events":[{"name":{"ne":"पितृ विसर्जन","en":"Pitri Bisarjan"},"jbo":"NS"},{"name":{"ne":"औंसी श्राद्ध","en":"Aausi Shraddha"},"jbo":"NS"},{"name":{"ne":"विश्वकर्मा पूजा","en":"Bishwakarma Pooja"},"jbo":"BS"},{"name":{"ne":"वास्तु दिवस","en":"Vaastu Diwas"},"jbo":"BS"},{"name":{"ne":"राष्ट्रि्य विज्ञान दिवस","en":"National Science Day"},"jbo":"BS"},{"name":{"ne":"आश्विन संक्रान्ति","en":"Ashwin Sankranti"},"jbo":"BS"}],"saits":[],"panchanga":{"ad":"२०२०","saksambat":"१९४२","sambatsar":"प्रमादी","ayen":"दक्षिणायन","ritu":"शरद","nsyear":"११४०","nsmonth":"ञलगा","chandramasa":"आश्विन कृष्णपक्ष","tithi_name":"औंसी , १६:५९  बजे उप्रान्त प्रतिपदा ","nakshatra":"पूर्वफाल्गुनी , १०:५३  बजे उप्रान्त उत्तरफाल्गुनी ","yog":"शुभ , २६:४४  बजे उप्रान्त शुक्ल ","karan":"चतुष्पद  ०६:०१  बजेदेखि नाग , १६:५९  बजे उप्रान्त कौलव ","anandiyog":"गद","chandrarashi":"सिंह","sunrise":"०५:५०","sunset":"१८:०४","dinman":"३०।३५","parba":"आश्विन संक्रान्ति। दर्श-श्राद्ध। औंसी श्राद्ध। पितृ विसर्जन, सोह्रश्राद्ध समाप्ति। हलो तथा निशि बार्ने औंसी।  विश्वकर्मा पूजा। वास्तु दिवस।","surya":"४:२९:४८:१४","chandra":"४:२३:४२:२६","mangal":"११:२२:४५:४०","budha":"५:२४:४६:२०","brihaspati":"८:२४:४१:५९","sukra":"३:१८:३२:५०","sani":"८:२७:५२:५२","rahu":"१:२९:३७:५२","kranti":"उ. २:१६","belantar":"(–) ६:२२","birthname":[{"dt":"10:53","nakshatra":"टु"},{"dt":"16:33","nakshatra":"टे"},{"dt":"22:12","nakshatra":"टो"},{"dt":"27:50","nakshatra":"पा"}]}},{"quarter":2,"week":38,"day":5,"date":2,"ad":"2020-09-18","bs":"02.06.2077","tithi":0,"nsYear":1140,"nsMonth":25,"chandrama":22.1,"events":[],"saits":[],"panchanga":{"ad":"२०२०","saksambat":"१९४२","sambatsar":"प्रमादी","ayen":"दक्षिणायन","ritu":"शरद","nsyear":"११४०","nsmonth":"ञलगा","chandramasa":"अधिक आश्विन शुक्लपक्ष","tithi_name":"प्रतिपदा , १४:४६  बजे उप्रान्त द्वितिय ","nakshatra":"उत्तरफाल्गुनी , ०९:२८  बजे उप्रान्त हस्त ","yog":"शुक्ल , २३:४६  बजे उप्रान्त ब्रह्म ","karan":"वव  १४:४६  बजेदेखि वालव , २५:३६  बजे उप्रान्त गर ","anandiyog":"शुभ","chandrarashi":"कन्या","sunrise":"०५:५१","sunset":"१८:०३","dinman":"३०।३१","parba":"चन्द्रोदय। अधिक मास (मलमास) प्रारम्भ। अपूप दान सुरु। मत्स्यनारायण मेला प्रारम्भ। ","surya":"५:००:४६:४९","chandra":"५:०७:५१:१४","mangal":"११:२२:३३:३४","budha":"५:२६:०९:४३","brihaspati":"८:२४:४२:२०","sukra":"३:१९:४१:१२","sani":"८:२७:५१:५४","rahu":"१:२९:३४:४१","kranti":"उ. १:५३","belantar":"(–) ६:५३","birthname":[{"dt":"9:28","nakshatra":"पि"},{"dt":"15:05","nakshatra":"पु"},{"dt":"20:42","nakshatra":"ष"},{"dt":"26:18","nakshatra":"ण"},{"dt":"31:53","nakshatra":"ठ"}]}},{"quarter":2,"week":38,"day":6,"date":3,"ad":"2020-09-19","bs":"03.06.2077","tithi":1,"nsYear":1140,"nsMonth":25,"chandrama":22.1,"events":[{"name":{"ne":"संविधान दिवस","en":"Constitution Day"},"jbo":"BS","gh":1}],"gh":1,"saits":[],"panchanga":{"ad":"२०२०","saksambat":"१९४२","sambatsar":"प्रमादी","ayen":"दक्षिणायन","ritu":"शरद","nsyear":"११४०","nsmonth":null,"chandramasa":"अधिक आश्विन शुक्लपक्ष","tithi_name":"द्वितिय , १२:२४  बजे उप्रान्त तृतीया ","nakshatra":"हस्त , ०७:५३  बजे उप्रान्त चित्रा ","yog":"ब्रह्म , २०:४१  बजे उप्रान्त ऐन्द्र ","karan":"कौलव  १२:२४  बजेदेखि तैतिल , २३:११  बजे उप्रान्त भद्रा ","anandiyog":"मृत्यु","chandrarashi":"कन्या","sunrise":"०५:५१","sunset":"१८:०२","dinman":"३०।२७","parba":"संविधान दिवस। द्विपुष्कर योग ७:५३ देखि १२:२४ बजेसम्म। ","surya":"५:०१:४५:२७","chandra":"५:२२:०७:१०","mangal":"११:२२:२०:५१","budha":"५:२७:३०:४६","brihaspati":"८:२४:४२:५३","sukra":"३:२०:४९:४३","sani":"८:२७:५१:०२","rahu":"१:२९:३१:३०","kranti":"उ. १:२९","belantar":"(–) ७:१४","birthname":[{"dt":"7:53","nakshatra":"ठ"},{"dt":"13:29","nakshatra":"पे"},{"dt":"19:04","nakshatra":"पो"},{"dt":"24:39","nakshatra":"रा"},{"dt":"30:13","nakshatra":"रि"}]}},{"quarter":2,"week":38,"day":0,"date":4,"ad":"2020-09-20","bs":"04.06.2077","tithi":2,"nsYear":1140,"nsMonth":25,"chandrama":22.1,"events":[],"saits":[],"panchanga":{"ad":"२०२०","saksambat":"१९४२","sambatsar":"प्रमादी","ayen":"दक्षिणायन","ritu":"शरद","nsyear":"११४०","nsmonth":null,"chandramasa":"अधिक आश्विन शुक्लपक्ष","tithi_name":"तृतीया , ०९:५८  बजे उप्रान्त चतुर्थी ","nakshatra":"चित्रा  ०६:१३  बजेदेखि स्वाती , २८:३४  बजे उप्रान्त अनुराधा ","yog":"ऐन्द्र , १७:३५  बजे उप्रान्त वैधृति ","karan":"गर  ०९:५८  बजेदेखि वणिज , २०:४५  बजे उप्रान्त कौलव ","anandiyog":"पद्म","chandrarashi":"तुला","sunrise":"०५:५२","sunset":"१८:०१","dinman":"३०।२३","parba":"","surya":"५:०२:४४:०६","chandra":"६:०६:२६:५७","mangal":"११:२२:०७:३३","budha":"५:२८:४९:२०","brihaspati":"८:२४:४३:३९","sukra":"३:२१:५८:२३","sani":"८:२७:५०:१६","rahu":"१:२९:२८:१९","kranti":"उ. १:०६","belantar":"(–) ७:३६","birthname":[{"dt":"6:13","nakshatra":"रि"},{"dt":"11:48","nakshatra":"रु"},{"dt":"17:23","nakshatra":"रे"},{"dt":"22:58","nakshatra":"रो"},{"dt":"28:34","nakshatra":"ता"}]}},{"quarter":2,"week":39,"day":1,"date":5,"ad":"2020-09-21","bs":"05.06.2077","tithi":3,"nsYear":1140,"nsMonth":25,"chandrama":22.1,"events":[{"name":{"ne":"विश्व शान्ति दिवस","en":"World Peace Day"},"jbo":"AD"}],"saits":[],"panchanga":{"ad":"२०२०","saksambat":"१९४२","sambatsar":"प्रमादी","ayen":"दक्षिणायन","ritu":"शरद","nsyear":"११४०","nsmonth":null,"chandramasa":"अधिक आश्विन शुक्लपक्ष","tithi_name":"चतुर्थी  ०७:३३  बजेदेखि पञ्चमी , २९:१४  बजे उप्रान्त सप्तमी ","nakshatra":"विशाखा , २६:५९  बजे उप्रान्त अनुराधा ","yog":"वैधृति , १४:३२  बजे उप्रान्त विष्कम्भ ","karan":"भद्रा  ०७:३३  बजेदेखि वव , १८:२३  बजे उप्रान्त गर ","anandiyog":"मित्र","chandrarashi":"तुला","sunrise":"०५:५२","sunset":"१८:००","dinman":"३०।१९","parba":"विश्व शान्ति दिवस।  सर्वार्थसिद्धि योग २६:५९ बजेपछि। ","surya":"५:०३:४२:४९","chandra":"६:२०:४६:४४","mangal":"११:२१:५३:४१","budha":"६:००:०५:१३","brihaspati":"८:२४:४४:३७","sukra":"३:२३:०७:१०","sani":"८:२७:४९:३७","rahu":"१:२९:२५:०८","kranti":"उ. ०:४३","belantar":"(–) ७:५७","birthname":[{"dt":"10:09","nakshatra":"ति"},{"dt":"15:45","nakshatra":"तु"},{"dt":"21:22","nakshatra":"ते"},{"dt":"26:59","nakshatra":"तो"},{"dt":"32:37","nakshatra":"ना"}]}},{"quarter":2,"week":39,"day":2,"date":6,"ad":"2020-09-22","bs":"06.06.2077","tithi":5,"nsYear":1140,"nsMonth":25,"chandrama":22.1,"events":[{"name":{"ne":"सामाजिक सेवा दिवस","en":"Social Service Day"},"jbo":"BS"}],"saits":[],"panchanga":{"ad":"२०२०","saksambat":"१९४२","sambatsar":"प्रमादी","ayen":"दक्षिणायन","ritu":"शरद","nsyear":"११४०","nsmonth":null,"chandramasa":"अधिक आश्विन शुक्लपक्ष","tithi_name":"षष्ठी , २७:०६  बजे उप्रान्त सप्तमी ","nakshatra":"अनुराधा , २५:३५  बजे उप्रान्त ज्येष्ठा ","yog":"विष्कम्भ , ११:३४  बजे उप्रान्त प्रीति ","karan":"कौलव  १६:०९  बजेदेखि तैतिल , २७:०६  बजे उप्रान्त भद्रा ","anandiyog":"वज्र","chandrarashi":"वृश्चिक","sunrise":"०५:५३","sunset":"१७:५८","dinman":"३०।१५","parba":"तुला राशिमा सायन सूर्य २५:४३ बजे प्रवेश।","surya":"५:०४:४१:३३","chandra":"७:०५:०२:३९","mangal":"११:२१:३९:२०","budha":"६:०१:१८:१६","brihaspati":"८:२४:४५:४७","sukra":"३:२४:१६:०६","sani":"८:२७:४९:०४","rahu":"१:२९:२१:५७","kranti":"उ. ०:१९","belantar":"(–) ८:१८","birthname":[{"dt":"8:37","nakshatra":"ना"},{"dt":"14:15","nakshatra":"नि"},{"dt":"19:55","nakshatra":"नु"},{"dt":"25:35","nakshatra":"ने"},{"dt":"31:16","nakshatra":"नो"}]}},{"quarter":2,"week":39,"day":3,"date":7,"ad":"2020-09-23","bs":"07.06.2077","tithi":6,"nsYear":1140,"nsMonth":25,"chandrama":22.1,"events":[],"saits":[],"panchanga":{"ad":"२०२०","saksambat":"१९४२","sambatsar":"प्रमादी","ayen":"दक्षिणायन","ritu":"शरद","nsyear":"११४०","nsmonth":null,"chandramasa":"अधिक आश्विन शुक्लपक्ष","tithi_name":"सप्तमी , २५:१३  बजे उप्रान्त अष्टमी ","nakshatra":"ज्येष्ठा , २४:२५  बजे उप्रान्त मूल ","yog":"प्रीति , ०८:४६  बजे उप्रान्त आयुष्मान् ","karan":"गर  १४:०७  बजेदेखि वणिज , २५:१३  बजे उप्रान्त वालव ","anandiyog":"ध्वांक्ष","chandrarashi":"वृश्चिक","sunrise":"०५:५३","sunset":"१७:५७","dinman":"३०।११","parba":"","surya":"५:०५:४०:१९","chandra":"७:१९:११:२६","mangal":"११:२१:२४:३२","budha":"६:०२:२८:१६","brihaspati":"८:२४:४७:१०","sukra":"३:२५:२५:०९","sani":"८:२७:४८:३८","rahu":"१:२९:१८:४७","kranti":"द. ०:०४","belantar":"(–) ८:३९","birthname":[{"dt":"7:16","nakshatra":"नो"},{"dt":"12:58","nakshatra":"या"},{"dt":"18:41","nakshatra":"यि"},{"dt":"24:25","nakshatra":"यु"},{"dt":"30:10","nakshatra":"ये"}]}},{"quarter":2,"week":39,"day":4,"date":8,"ad":"2020-09-24","bs":"08.06.2077","tithi":7,"nsYear":1140,"nsMonth":25,"chandrama":22.1,"events":[],"saits":[],"panchanga":{"ad":"२०२०","saksambat":"१९४२","sambatsar":"प्रमादी","ayen":"दक्षिणायन","ritu":"शरद","nsyear":"११४०","nsmonth":null,"chandramasa":"अधिक आश्विन शुक्लपक्ष","tithi_name":"अष्टमी , २३:३९  बजे उप्रान्त नवमी ","nakshatra":"मूल , २३:३४  बजे उप्रान्त पूर्वाषाढा ","yog":"आयुष्मान्  ०६:११  बजेदेखि सौभाग्य , २७:५२  बजे उप्रान्त अतिगण्ड ","karan":"भद्रा  १२:२३  बजेदेखि वव , २३:३९  बजे उप्रान्त तैतिल ","anandiyog":"धुम्र","chandrarashi":"धनु","sunrise":"०५:५३","sunset":"१७:५६","dinman":"३०।०६","parba":"अष्टमी व्रत। गोरखकाली पूजा।","surya":"५:०६:३९:०८","chandra":"८:०३:१०:१०","mangal":"११:२१:०९:२०","budha":"६:०३:३५:०१","brihaspati":"८:२४:४८:४५","sukra":"३:२६:३४:२०","sani":"८:२७:४८:१८","rahu":"१:२९:१५:३६","kranti":"द. ०:२७","belantar":"(–) ८:५९","birthname":[{"dt":"6:10","nakshatra":"ये"},{"dt":"11:57","nakshatra":"यो"},{"dt":"17:45","nakshatra":"भा"},{"dt":"23:34","nakshatra":"भि"},{"dt":"29:25","nakshatra":"भु"}]}},{"quarter":2,"week":39,"day":5,"date":9,"ad":"2020-09-25","bs":"09.06.2077","tithi":8,"nsYear":1140,"nsMonth":25,"chandrama":22.1,"events":[],"saits":[],"panchanga":{"ad":"२०२०","saksambat":"१९४२","sambatsar":"प्रमादी","ayen":"दक्षिणायन","ritu":"शरद","nsyear":"११४०","nsmonth":null,"chandramasa":"अधिक आश्विन शुक्लपक्ष","tithi_name":"नवमी , २२:२८  बजे उप्रान्त दशमी ","nakshatra":"पूर्वाषाढा , २३:०६  बजे उप्रान्त उत्तराषाढा ","yog":"शोभन , २५:५२  बजे उप्रान्त अतिगण्ड ","karan":"वालव  ११:००  बजेदेखि कौलव , २२:२८  बजे उप्रान्त वणिज ","anandiyog":"प्रवर्द्ध","chandrarashi":"धनु","sunrise":"०५:५४","sunset":"१७:५५","dinman":"३०।०२","parba":"","surya":"५:०७:३७:५९","chandra":"८:१६:५६:२८","mangal":"११:२०:५३:४६","budha":"६:०४:३८:१७","brihaspati":"८:२४:५०:३२","sukra":"३:२७:४३:३९","sani":"८:२७:४८:०५","rahu":"१:२९:१२:२५","kranti":"द. ०:५१","belantar":"(–) ९:२०","birthname":[{"dt":"11:17","nakshatra":"धा"},{"dt":"17:11","nakshatra":"फा"},{"dt":"23:06","nakshatra":"ढा"},{"dt":"29:03","nakshatra":"भे"}]}},{"quarter":2,"week":39,"day":6,"date":10,"ad":"2020-09-26","bs":"10.06.2077","tithi":9,"nsYear":1140,"nsMonth":25,"chandrama":22.1,"events":[],"saits":[],"panchanga":{"ad":"२०२०","saksambat":"१९४२","sambatsar":"प्रमादी","ayen":"दक्षिणायन","ritu":"शरद","nsyear":"११४०","nsmonth":null,"chandramasa":"अधिक आश्विन शुक्लपक्ष","tithi_name":"दशमी , २१:४४  बजे उप्रान्त एकादशी ","nakshatra":"उत्तराषाढा , २३:०५  बजे उप्रान्त श्रवण ","yog":"अतिगण्ड , २४:१४  बजे उप्रान्त सुकर्मा ","karan":"तैतिल  १०:०३  बजेदेखि गर , २१:४४  बजे उप्रान्त वव ","anandiyog":"राक्षस","chandrarashi":"मकर","sunrise":"०५:५४","sunset":"१७:५४","dinman":"२९।५८","parba":"सर्वार्थसिद्धि योग २३:०५ बजेपछि। ","surya":"५:०८:३६:५२","chandra":"९:००:२८:३३","mangal":"११:२०:३७:५३","budha":"६:०५:३७:५०","brihaspati":"८:२४:५२:३१","sukra":"३:२८:५३:०५","sani":"८:२७:४७:५८","rahu":"१:२९:०९:१४","kranti":"द. १:१४","belantar":"(–) ९:४१","birthname":[{"dt":"11:02","nakshatra":"भो"},{"dt":"17:02","nakshatra":"जा"},{"dt":"23:05","nakshatra":"जि"},{"dt":"29:09","nakshatra":"खि"}]}},{"quarter":2,"week":39,"day":0,"date":11,"ad":"2020-09-27","bs":"11.06.2077","tithi":10,"nsYear":1140,"nsMonth":25,"chandrama":22.1,"events":[{"name":{"ne":"विश्व पर्यटक दिवस","en":"World Tourism Day"},"jbo":"AD"}],"saits":[],"panchanga":{"ad":"२०२०","saksambat":"१९४२","sambatsar":"प्रमादी","ayen":"दक्षिणायन","ritu":"शरद","nsyear":"११४०","nsmonth":null,"chandramasa":"अधिक आश्विन शुक्लपक्ष","tithi_name":"एकादशी , २१:२९  बजे उप्रान्त द्वादशी ","nakshatra":"श्रवण , २३:३२ बजे उप्रान्त धनिष्ठा ","yog":"सुकर्मा , २२:५९  बजे उप्रान्त धृति ","karan":"वणिज  ०९:३३  बजेदेखि भद्रा , २१:२९  बजे उप्रान्त कौलव ","anandiyog":"गद","chandrarashi":"मकर","sunrise":"०५:५५","sunset":"१७:५३","dinman":"२९।५४","parba":"पद्मिनी एकादशी व्रत। पर्यटन दिवस। द्विपुष्कर योग २३:३२ बजेपछि।","surya":"५:०९:३५:४८","chandra":"९:१३:४५:२४","mangal":"११:२०:२१:४४","budha":"६:०६:३३:२७","brihaspati":"८:२४:५४:४२","sukra":"४:००:०२:३८","sani":"८:२७:४७:५७","rahu":"१:२९:०६:०३","kranti":"द. १:३८","belantar":"(–) १०:०१","birthname":[{"dt":"11:14","nakshatra":"खु"},{"dt":"17:22","nakshatra":"खे"},{"dt":"23:32","nakshatra":"खो"},{"dt":"29:43","nakshatra":"गा"}]}},{"quarter":2,"week":40,"day":1,"date":12,"ad":"2020-09-28","bs":"12.06.2077","tithi":11,"nsYear":1140,"nsMonth":25,"chandrama":22.1,"events":[{"name":{"ne":"रेबिजविरुद्ध दिवस","en":"World Rabies Day"},"jbo":"AD"}],"saits":[],"panchanga":{"ad":"२०२०","saksambat":"१९४२","sambatsar":"प्रमादी","ayen":"दक्षिणायन","ritu":"शरद","nsyear":"११४०","nsmonth":null,"chandramasa":"अधिक आश्विन शुक्लपक्ष","tithi_name":"द्वादशी , २१:४५  बजे उप्रान्त त्रयोदशी ","nakshatra":"धनिष्ठा , २४:२८  बजे उप्रान्त शतभिषा ","yog":"धृति , २२:०८  बजे उप्रान्त शूल ","karan":"वव  ०९:३४  बजेदेखि वालव , २१:४५  बजे उप्रान्त गर ","anandiyog":"शुभ","chandrarashi":"मकर","sunrise":"०५:५५","sunset":"१७:५१","dinman":"२९।५०","parba":"धनिष्ठा पञ्चक ११:५६ बजे प्रारम्भ।","surya":"५:१०:३४:४६","chandra":"९:२६:४६:४०","mangal":"११:२०:०५:२१","budha":"६:०७:२४:५२","brihaspati":"८:२४:५७:०५","sukra":"४:०१:१२:१९","sani":"८:२७:४८:०४","rahu":"१:२९:०२:५३","kranti":"द. २:०१","belantar":"(–) १०:२१","birthname":[{"dt":"11:56","nakshatra":"गि"},{"dt":"18:11","nakshatra":"गु"},{"dt":"24:28","nakshatra":"गे"},{"dt":"30:47","nakshatra":"गो"}]}},{"quarter":2,"week":40,"day":2,"date":13,"ad":"2020-09-29","bs":"13.06.2077","tithi":12,"nsYear":1140,"nsMonth":25,"chandrama":22.1,"events":[{"name":{"ne":"विश्व हृदय दिवस","en":"World Heart Day"},"jbo":"AD"}],"saits":[],"panchanga":{"ad":"२०२०","saksambat":"१९४२","sambatsar":"प्रमादी","ayen":"दक्षिणायन","ritu":"शरद","nsyear":"११४०","nsmonth":null,"chandramasa":"अधिक आश्विन शुक्लपक्ष","tithi_name":"त्रयोदशी , २२:३२  बजे उप्रान्त चतुर्दशी ","nakshatra":"शतभिषा , २५:५५  बजे उप्रान्त पूर्वभाद्रपदा ","yog":"शूल , २१:४०  बजे उप्रान्त गण्ड ","karan":"कौलव  १०:०५  बजेदेखि तैतिल , २२:३२  बजे उप्रान्त भद्रा ","anandiyog":"मृत्यु","chandrarashi":"कुम्भ","sunrise":"०५:५६","sunset":"१७:५०","dinman":"२९।४६","parba":"पञ्चक। प्रदोष व्रत। ","surya":"५:११:३३:३४","chandra":"१०:०९:३२:५२","mangal":"११:१९:४८:४९","budha":"६:०८:११:४८","brihaspati":"८:२४:५९:४०","sukra":"४:०२:२२:०६","sani":"८:२७:४८:१६","rahu":"१:२८:५९:४२","kranti":"द. २:३४","belantar":"(–) १०:४०","birthname":[{"dt":"6:47","nakshatra":"गो"},{"dt":"13:08","nakshatra":"सा"},{"dt":"19:31","nakshatra":"सि"},{"dt":"25:55","nakshatra":"सु"},{"dt":"32:21","nakshatra":"से"}]}},{"quarter":2,"week":40,"day":3,"date":14,"ad":"2020-09-30","bs":"14.06.2077","tithi":13,"nsYear":1140,"nsMonth":25,"chandrama":22.1,"events":[],"saits":[],"panchanga":{"ad":"२०२०","saksambat":"१९४२","sambatsar":"प्रमादी","ayen":"दक्षिणायन","ritu":"शरद","nsyear":"११४०","nsmonth":null,"chandramasa":"अधिक आश्विन शुक्लपक्ष","tithi_name":"चतुर्दशी , २३:४७  बजे उप्रान्त पूर्णिमा ","nakshatra":"पूर्वभाद्रपदा , २७:४८  बजे उप्रान्त उत्तरभाद्रपदा ","yog":"गण्ड , २१:३५  बजे उप्रान्त वृद्धि ","karan":"गर  ११:०६  बजेदेखि वणिज , २३:४७  बजे उप्रान्त वालव ","anandiyog":"पद्म","chandrarashi":"कुम्भ","sunrise":"०५:५६","sunset":"१७:४९","dinman":"२९।४२","parba":"पञ्चक।","surya":"५:१२:३२:४८","chandra":"१०:२२:०५:१३","mangal":"११:१९:३२:०९","budha":"६:०८:५४:०१","brihaspati":"८:२५:०२:२८","sukra":"४:०३:३२:०१","sani":"८:२७:४८:३५","rahu":"१:१८:५६:३१","kranti":"द. २:४८","belantar":"(–) ११:००","birthname":[{"dt":"8:21","nakshatra":"से"},{"dt":"14:48","nakshatra":"सो"},{"dt":"21:18","nakshatra":"दा"},{"dt":"27:48","nakshatra":"दि"}]}},{"quarter":2,"week":40,"day":4,"date":15,"ad":"2020-10-01","bs":"15.06.2077","tithi":14,"nsYear":1140,"nsMonth":25,"chandrama":22.1,"events":[{"name":{"ne":"अन्तर्राष्ट्रि्य वृद्ध दिवस","en":"International Day of Older Persons"},"jbo":"AD"}],"saits":[],"panchanga":{"ad":"२०२०","saksambat":"१९४२","sambatsar":"प्रमादी","ayen":"दक्षिणायन","ritu":"शरद","nsyear":"११४०","nsmonth":null,"chandramasa":"अधिक आश्विन शुक्लपक्ष","tithi_name":"पूर्णिमा , २५:२७  बजे उप्रान्त प्रतिपदा ","nakshatra":"उत्तरभाद्रपदा , ३०:०४  बजे उप्रान्त रेवती ","yog":"वृद्धि , २१:४८  बजे उप्रान्त ध्रुव ","karan":"भद्रा  १२:३४  बजेदेखि वव , २५:२७  बजे उप्रान्त तैतिल ","anandiyog":"छत्र","chandrarashi":"मीन","sunrise":"०५:५७","sunset":"१७:४८","dinman":"२९।३८","parba":"पञ्चक। पूर्णिमा व्रत। अनला पुन्ही।","surya":"५:१३:३१:५३","chandra":"११:०४:२५:३७","mangal":"११:१९:१५:२५","budha":"६:०९:३१:१३","brihaspati":"८:२५:०५:२७","sukra":"४:०४:४२:०१","sani":"८:२७:४९:०१","rahu":"१:२८:५३:२०","kranti":"द. ३:११","belantar":"(–) ११:१९","birthname":[{"dt":"10:20","nakshatra":"दु"},{"dt":"16:54","nakshatra":"थ"},{"dt":"23:28","nakshatra":"झ"},{"dt":"30:04","nakshatra":"ञ"}]}},{"quarter":2,"week":40,"day":5,"date":16,"ad":"2020-10-02","bs":"16.06.2077","tithi":0,"nsYear":1140,"nsMonth":25,"chandrama":21.2,"events":[{"name":{"ne":"अन्तर्राष्ट्रिय अहिंसा दिवस","en":"International Day of Non-Violence"},"jbo":"AD"}],"saits":[],"panchanga":{"ad":"२०२०","saksambat":"१९४२","sambatsar":"प्रमादी","ayen":"दक्षिणायन","ritu":"शरद","nsyear":"११४०","nsmonth":null,"chandramasa":"अधिक आश्विन कृष्णपक्ष","tithi_name":"प्रतिपदा , २७:२४  बजे उप्रान्त द्वितिय ","nakshatra":"उत्तरभाद्रपदा , ०६:४०  बजे उप्रान्त रेवती ","yog":"ध्रुव , २२:१५  बजे उप्रान्त व्याघात ","karan":"वालव  १४:२४  बजेदेखि कौलव , २७:२४  बजे उप्रान्त वणिज ","anandiyog":"ध्वज","chandrarashi":"मीन","sunrise":"०५:५७","sunset":"१७:४७","dinman":"२९।३४","parba":"पञ्चक।","surya":"५:१४:३१:००","chandra":"११:१६:३६:३७","mangal":"११:१८:५८:४०","budha":"६:१०:०३:०९","brihaspati":"८:२५:०८:३७","sukra":"४:०५:५२:०९","sani":"८:२७:४९:३३","rahu":"१:२८:५०:०९","kranti":"द. ३:३४","belantar":"(–) ११:३८","birthname":[{"dt":"6:04","nakshatra":"ञ"},{"dt":"12:41","nakshatra":"दे"},{"dt":"19:18","nakshatra":"दो"},{"dt":"25:56","nakshatra":"चा"},{"dt":"32:35","nakshatra":"चि"}]}},{"quarter":2,"week":40,"day":6,"date":17,"ad":"2020-10-03","bs":"17.06.2077","tithi":1,"nsYear":1140,"nsMonth":25,"chandrama":21.2,"events":[],"saits":[],"panchanga":{"ad":"२०२०","saksambat":"१९४२","sambatsar":"प्रमादी","ayen":"दक्षिणायन","ritu":"शरद","nsyear":"११४०","nsmonth":null,"chandramasa":"अधिक आश्विन कृष्णपक्ष","tithi_name":"द्वितिय , २९:२९  बजे उप्रान्त तृतीया ","nakshatra":"रेवती , ०८:३५  बजे उप्रान्त अश्विनी ","yog":"व्याघात , २२:५०  बजे उप्रान्त हर्षण ","karan":"तैतिल  १६:२६  बजेदेखि गर , २९:२९  बजे उप्रान्त भद्रा ","anandiyog":"धाता","chandrarashi":"मीन","sunrise":"०५:५८","sunset":"१७:४६","dinman":"२९।३०","parba":"पञ्चक ८:३५ बजे समाप्ति।","surya":"५:१५:३०:०९","chandra":"११:२८:४१:१२","mangal":"११:१८:४१:५६","budha":"६:१०:२९:३४","brihaspati":"८:२५:१२:००","sukra":"४:०७:०२:२३","sani":"८:२७:५०:११","rahu":"१:२८:४६:५९","kranti":"द. ३:३८","belantar":"(–) ११:५७","birthname":[{"dt":"8:35","nakshatra":"चि"},{"dt":"15:14","nakshatra":"चु"},{"dt":"21:53","nakshatra":"चे"},{"dt":"28:33","nakshatra":"चो"}]}},{"quarter":2,"week":40,"day":0,"date":18,"ad":"2020-10-04","bs":"18.06.2077","tithi":2,"nsYear":1140,"nsMonth":25,"chandrama":21.2,"events":[],"saits":[],"panchanga":{"ad":"२०२०","saksambat":"१९४२","sambatsar":"प्रमादी","ayen":"दक्षिणायन","ritu":"शरद","nsyear":"११४०","nsmonth":null,"chandramasa":"अधिक आश्विन कृष्णपक्ष","tithi_name":"तृतीया , ३१:३३  बजे उप्रान्त चतुर्थी ","nakshatra":"अश्विनी , ११:१२  बजे उप्रान्त भरणी ","yog":"हर्षण , २३:२५  बजे उप्रान्त वज्र ","karan":"वणिज  १८:३२  बजेदेखि भद्रा , ४४:३०  बजे उप्रान्त वालव ","anandiyog":"आनन्द","chandrarashi":"मेष","sunrise":"०५:५८","sunset":"१७:४५","dinman":"२९।२६","parba":"सर्वार्थसिद्धि योग ११:१२ बजेसम्म। ","surya":"५:१६:२९:२०","chandra":"०:१०:४२:४४","mangal":"११:१८:२५:१८","budha":"६:१०:५०:१२","brihaspati":"८:२५:१५:३४","sukra":"४:०८:१२:४३","sani":"८:२७:५०:५६","rahu":"१:२८:४३:४८","kranti":"द. ४:२१","belantar":"(–) १२:१५","birthname":[{"dt":"11:12","nakshatra":"ला"},{"dt":"17:51","nakshatra":"लि"},{"dt":"24:30","nakshatra":"लु"},{"dt":"31:08","nakshatra":"ले"}]}},{"quarter":2,"week":41,"day":1,"date":19,"ad":"2020-10-05","bs":"19.06.2077","tithi":2,"nsYear":1140,"nsMonth":25,"chandrama":21.2,"events":[{"name":{"ne":"विश्व शिक्षक दिवस","en":"World Teachers' Day"},"jbo":"AD"}],"saits":[],"panchanga":{"ad":"२०२०","saksambat":"१९४२","sambatsar":"प्रमादी","ayen":"दक्षिणायन","ritu":"शरद","nsyear":"११४०","nsmonth":null,"chandramasa":"अधिक आश्विन कृष्णपक्ष","tithi_name":"तृतीया , ०७:३३  बजे उप्रान्त चतुर्थी ","nakshatra":"भरणी , १३:४५  बजे उप्रान्त कृत्तिका ","yog":"वज्र , २३:५४  बजे उप्रान्त सिद्धि ","karan":"भद्रा  ०७:३३  बजेदेखि वव , २०:३०  बजे उप्रान्त तैतिल ","anandiyog":"चर","chandrarashi":"मेष","sunrise":"०५:५९","sunset":"१७:४३","dinman":"२९।२१","parba":"सर्वार्थसिद्धि योग १३:४५ बजेपछि।","surya":"५:१७:२८:३४","chandra":"०:२२:४५:१४","mangal":"११:१८:०८:४८","budha":"६:११:०४:५०","brihaspati":"८:२५:१९:१९","sukra":"४:०९:२३:१०","sani":"८:२७:५१:४८","rahu":"१:२८:४०:३७","kranti":"द. ४:४४","belantar":"(–) १२:३३","birthname":[{"dt":"7:08","nakshatra":"ले"},{"dt":"13:45","nakshatra":"लो"},{"dt":"20:22","nakshatra":"अ"},{"dt":"26:57","nakshatra":"इ"}]}},{"quarter":2,"week":41,"day":2,"date":20,"ad":"2020-10-06","bs":"20.06.2077","tithi":3,"nsYear":1140,"nsMonth":25,"chandrama":21.2,"events":[{"name":{"ne":"मंगल-चतुर्थी व्रत","en":"Mangal Chaturthi Brata"},"jbo":"NS"}],"saits":[],"panchanga":{"ad":"२०२०","saksambat":"१९४२","sambatsar":"प्रमादी","ayen":"दक्षिणायन","ritu":"शरद","nsyear":"११४०","nsmonth":null,"chandramasa":"अधिक आश्विन कृष्णपक्ष","tithi_name":"चतुर्थी , ०९:२४  बजे उप्रान्त पञ्चमी ","nakshatra":"कृत्तिका , १६:०५  बजे उप्रान्त रोहिणी ","yog":"सिद्धि , २४:०९  बजे उप्रान्त व्यतीपात ","karan":"वालव  ०९:२४  बजेदेखि कौलव , २२:१३  बजे उप्रान्त वालव ","anandiyog":"गद","chandrarashi":"वृष","sunrise":"०५:५९","sunset":"१७:४२","dinman":"२९।१७","parba":"सर्वार्थसिद्धि योग १६:०५ बजेसम्म। मंगल–चौथी व्रत।","surya":"५:१८:२७:५०","chandra":"१:०४:५२:२२","mangal":"११:१७:५२:३३","budha":"६:११:१३:१८","brihaspati":"८:२५:२३:१६","sukra":"४:१०:३३:४३","sani":"८:२७:५२:४६","rahu":"१:२८:३७:२६","kranti":"द. ५:०७","belantar":"(–) १२:५०","birthname":[{"dt":"9:31","nakshatra":"उ"},{"dt":"16:05","nakshatra":"ए"},{"dt":"22:36","nakshatra":"ओ"},{"dt":"29:07","nakshatra":"बा"}]}},{"quarter":2,"week":41,"day":3,"date":21,"ad":"2020-10-07","bs":"21.06.2077","tithi":4,"nsYear":1140,"nsMonth":25,"chandrama":21.2,"events":[],"saits":[1],"panchanga":{"ad":"२०२०","saksambat":"१९४२","sambatsar":"प्रमादी","ayen":"दक्षिणायन","ritu":"शरद","nsyear":"११४०","nsmonth":null,"chandramasa":"अधिक आश्विन कृष्णपक्ष","tithi_name":"पञ्चमी , १०:५५  बजे उप्रान्त पञ्चमी ","nakshatra":"रोहिणी , १८:०३  बजे उप्रान्त रोहिणी ","yog":"व्यतीपात , २४:०६  बजे उप्रान्त व्यतीपात ","karan":"तैतिल  १०:५५  बजेदेखि गर , २३:३२  बजे उप्रान्त तैतिल ","anandiyog":"शुभ","chandrarashi":"वृष","sunrise":"०६:००","sunset":"१७:४१","dinman":"२९।१३","parba":"सर्वार्थसिद्धि योग अहोरात्र। ","surya":"५:१९:२७:०८","chandra":"१:१७:०७:२०","mangal":"११:१७:३६:३३","budha":"६:११:१५:२७","brihaspati":"८:२५:२७:२५","sukra":"४:११:४४:२२","sani":"८:२७:५३:५०","rahu":"१:२८:३४:१५","kranti":"द. ५:३०","belantar":"(–) १३:०७","birthname":[{"dt":"11:36","nakshatra":"बि"},{"dt":"18:03","nakshatra":"बु"},{"dt":"24:28","nakshatra":"बे"},{"dt":"30:52","nakshatra":"बो"}]}},{"quarter":2,"week":41,"day":4,"date":22,"ad":"2020-10-08","bs":"22.06.2077","tithi":5,"nsYear":1140,"nsMonth":25,"chandrama":21.2,"events":[],"saits":[],"panchanga":{"ad":"२०२०","saksambat":"१९४२","sambatsar":"प्रमादी","ayen":"दक्षिणायन","ritu":"शरद","nsyear":"११४०","nsmonth":null,"chandramasa":"अधिक आश्विन कृष्णपक्ष","tithi_name":"","nakshatra":"","yog":"","karan":"","anandiyog":"पद्म","chandrarashi":"मिथुन","sunrise":"०६:०१","sunset":"१७:३९","dinman":"२९।०५","parba":"अष्टमी व्रत।","surya":"५:२१:२५:५२","chandra":"२:१२:११:२९","mangal":"११:१७:०५:३४","budha":"६:११:००:३३","brihaspati":"८:२५:३६:१५","sukra":"४:१४:०५:५७","sani":"८:२७:५६:१८","rahu":"१:२८:२७:५४","kranti":"द. ६:१६","belantar":"(–) १३:४०","birthname":[]}},{"quarter":2,"week":41,"day":5,"date":23,"ad":"2020-10-09","bs":"23.06.2077","tithi":6,"nsYear":1140,"nsMonth":25,"chandrama":21.2,"events":[{"name":{"ne":"विश्व हुलाक दिवस","en":"World Post Office Day"},"jbo":"AD"}],"saits":[],"panchanga":{"ad":"२०२०","saksambat":"१९४२","sambatsar":"प्रमादी","ayen":"दक्षिणायन","ritu":"शरद","nsyear":"११४०","nsmonth":null,"chandramasa":"अधिक आश्विन कृष्णपक्ष","tithi_name":"सप्तमी , १२:३६  बजे उप्रान्त अष्टमी ","nakshatra":"आर्द्रा , २०:३७  बजे उप्रान्त पुनर्वशु ","yog":"परिघ , २२:५२  बजे उप्रान्त शिव ","karan":"वव  १२:३६  बजेदेखि वालव , २४:४३  बजे उप्रान्त गर ","anandiyog":"पद्म","chandrarashi":"मिथुन","sunrise":"०६:०१","sunset":"१७:३९","dinman":"२९।०५","parba":"अष्टमी व्रत।","surya":"५:२१:२५:५२","chandra":"२:१२:११:२९","mangal":"११:१७:०५:३४","budha":"६:११:००:३३","brihaspati":"८:२५:३६:१५","sukra":"४:१४:०५:५७","sani":"८:२७:५६:१८","rahu":"१:२८:२७:५४","kranti":"द. ६:१६","belantar":"(–) १३:४०","birthname":[{"dt":"8:10","nakshatra":"घ"},{"dt":"14:25","nakshatra":"ङ"},{"dt":"20:37","nakshatra":"छ"},{"dt":"26:48","nakshatra":"के"},{"dt":"32:58","nakshatra":"को"}]}},{"quarter":2,"week":41,"day":6,"date":24,"ad":"2020-10-10","bs":"24.06.2077","tithi":7,"nsYear":1140,"nsMonth":25,"chandrama":21.2,"events":[{"name":{"ne":"विश्व मानसिक स्वास्थ दिवस","en":"World Mental Health day"},"jbo":"AD"}],"saits":[],"panchanga":{"ad":"२०२०","saksambat":"१९४२","sambatsar":"प्रमादी","ayen":"दक्षिणायन","ritu":"शरद","nsyear":"११४०","nsmonth":null,"chandramasa":"अधिक आश्विन कृष्णपक्ष","tithi_name":"अष्टमी , १२:४१  बजे उप्रान्त नवमी ","nakshatra":"पुनर्वशु , २१:१०  बजे उप्रान्त तिष्य ","yog":"शिव , २१:३९  बजे उप्रान्त सिद्ध ","karan":"कौलव  १२:४१  बजेदेखि तैतिल , २४:३२  बजे उप्रान्त भद्रा ","anandiyog":"छत्र","chandrarashi":"मिथुन","sunrise":"०६:०२","sunset":"१७:३८","dinman":"२९।०१","parba":"गोरखकाली पूजा।","surya":"५:२२:२५:१७","chandra":"२:२५:४:३१","mangal":"११:१६:५०:३८","budha":"६:१०:४३:३६","brihaspati":"८:२५:४०:५७","sukra":"४:१५:१६:४३","sani":"८:२७:५७:४१","rahu":"१:२८:२४:४३","kranti":"द. ६:३९","belantar":"(–) १३:५६","birthname":[{"dt":"8:58","nakshatra":"को"},{"dt":"15:05","nakshatra":"हा"},{"dt":"21:10","nakshatra":"हि"},{"dt":"27:14","nakshatra":"हु"}]}},{"quarter":2,"week":41,"day":0,"date":25,"ad":"2020-10-11","bs":"25.06.2077","tithi":8,"nsYear":1140,"nsMonth":25,"chandrama":21.2,"events":[{"name":{"ne":"गैर-आवासीय नेपाली दिवस","en":"NRN Day"},"jbo":"AD"}],"saits":[],"panchanga":{"ad":"२०२०","saksambat":"१९४२","sambatsar":"प्रमादी","ayen":"दक्षिणायन","ritu":"शरद","nsyear":"११४०","nsmonth":null,"chandramasa":"अधिक आश्विन कृष्णपक्ष","tithi_name":"नवमी , १२:१६  बजे उप्रान्त दशमी ","nakshatra":"तिष्य , २१:१४  बजे उप्रान्त अश्लेषा ","yog":"सिद्ध , २०:०३  बजे उप्रान्त साध्य ","karan":"गर  १२:१६  बजेदेखि वणिज , २३:५३  बजे उप्रान्त वालव ","anandiyog":"श्रीवत्स","chandrarashi":"कर्कट","sunrise":"०६:०२","sunset":"१७:३७","dinman":"२८।५७","parba":"","surya":"५:२३:२४:४४","chandra":"३:०८:१२:५७","mangal":"११:१६:३६:०९","budha":"६:१०:२०:३२","brihaspati":"८:२५:४५:५०","sukra":"४:१६:२७:५५","sani":"८:२७:५९:११","rahu":"१:२८:२१:३२","kranti":"द. ७:०२","belantar":"(–) १४:११","birthname":[{"dt":"9:16","nakshatra":"हे"},{"dt":"15:16","nakshatra":"हो"},{"dt":"21:14","nakshatra":"डा"},{"dt":"27:10","nakshatra":"डि"}]}},{"quarter":2,"week":42,"day":1,"date":26,"ad":"2020-10-12","bs":"26.06.2077","tithi":9,"nsYear":1140,"nsMonth":25,"chandrama":21.2,"events":[],"saits":[],"panchanga":{"ad":"२०२०","saksambat":"१९४२","sambatsar":"प्रमादी","ayen":"दक्षिणायन","ritu":"शरद","nsyear":"११४०","nsmonth":null,"chandramasa":"अधिक आश्विन कृष्णपक्ष","tithi_name":"दशमी , ११:२२  बजे उप्रान्त एकादशी ","nakshatra":"अश्लेषा , २०:५१  बजे उप्रान्त मघा ","yog":"साध्य , १८:०५  बजे उप्रान्त शुभ ","karan":"भद्रा  ११:२२  बजेदेखि वव , २२:४६  बजे उप्रान्त तैतिल ","anandiyog":"सौम्य","chandrarashi":"कर्कट","sunrise":"०६:०३","sunset":"१७:३६","dinman":"२८।५३","parba":"","surya":"५:२४:२४:१४","chandra":"३:२१:३६:५४","mangal":"११:१६:२२:०८","budha":"६:०९:५१:४०","brihaspati":"८:२५:५०:५४","sukra":"४:१७:३९:०२","sani":"८:२८:००:४७","rahu":"१:२८:१८:२१","kranti":"द. ७:२४","belantar":"(–) १४:२६","birthname":[{"dt":"9:05","nakshatra":"डु"},{"dt":"14:59","nakshatra":"डे"},{"dt":"20:51","nakshatra":"डो"},{"dt":"26:41","nakshatra":"मा"},{"dt":"32:30","nakshatra":"मि"}]}},{"quarter":2,"week":42,"day":2,"date":27,"ad":"2020-10-13","bs":"27.06.2077","tithi":10,"nsYear":1140,"nsMonth":25,"chandrama":21.2,"events":[{"name":{"ne":"प्राकृतिक विपत्ति न्यूनीकरण दिवस","en":"Natural Disaster Minimization Day"},"jbo":"AD"}],"saits":[],"panchanga":{"ad":"२०२०","saksambat":"१९४२","sambatsar":"प्रमादी","ayen":"दक्षिणायन","ritu":"शरद","nsyear":"११४०","nsmonth":null,"chandramasa":"अधिक आश्विन कृष्णपक्ष","tithi_name":"एकादशी , १०:०४  बजे उप्रान्त द्वादशी ","nakshatra":"मघा , २०:०४  बजे उप्रान्त पूर्वफाल्गुनी ","yog":"शुभ , १५:४८  बजे उप्रान्त शुक्ल ","karan":"वालव  १०:०४  बजेदेखि कौलव , २१:१६  बजे उप्रान्त वणिज ","anandiyog":"काल","chandrarashi":"सिंह","sunrise":"०६:०३","sunset":"१७:३५","dinman":"२८।४९","parba":"परमा एकादशी व्रत।","surya":"५:२५:२३:४६","chandra":"४:०५:१५:४४","mangal":"११:१६:०८:३७","budha":"६:०९:१७:२६","brihaspati":"८:२५:५६:०८","sukra":"४:१८:५०:१५","sani":"८:२८:०२:३०","rahu":"१:२८:१५:११","kranti":"द. ७:४७","belantar":"(–) १४:४०","birthname":[{"dt":"8:30","nakshatra":"मि"},{"dt":"14:18","nakshatra":"मु"},{"dt":"20:04","nakshatra":"मे"},{"dt":"25:49","nakshatra":"मो"},{"dt":"31:33","nakshatra":"टा"}]}},{"quarter":2,"week":42,"day":3,"date":28,"ad":"2020-10-14","bs":"28.06.2077","tithi":11,"nsYear":1140,"nsMonth":25,"chandrama":21.2,"events":[{"name":{"ne":"विश्व गुणस्तर दिवस","en":"World Quality Day"},"jbo":"AD"}],"saits":[],"panchanga":{"ad":"२०२०","saksambat":"१९४२","sambatsar":"प्रमादी","ayen":"दक्षिणायन","ritu":"शरद","nsyear":"११४०","nsmonth":null,"chandramasa":"अधिक आश्विन कृष्णपक्ष","tithi_name":"द्वादशी , ०८:२३  बजे उप्रान्त त्रयोदशी ","nakshatra":"पूर्वफाल्गुनी , १८:५८  बजे उप्रान्त उत्तरफाल्गुनी ","yog":"शुक्ल , १३:१४  बजे उप्रान्त ब्रह्म ","karan":"तैतिल  ०८:२३  बजेदेखि गर , १९:२६  बजे उप्रान्त चतुष्पद ","anandiyog":"स्थिर","chandrarashi":"सिंह","sunrise":"०६:०४","sunset":"१७:३४","dinman":"२८।४५","parba":"प्रदोष व्रत।","surya":"५:२६:२३:३०","chandra":"४:१९:०८:०३","mangal":"११:१५:५५:३८","budha":"६:०८:३८:२४","brihaspati":"८:२६:०१:३४","sukra":"४:२०:०१:३३","sani":"८:२८:०४:१८","rahu":"१:२८:१२:००","kranti":"द. ८:०९","belantar":"(–) १४:५४","birthname":[{"dt":"7:33","nakshatra":"टा"},{"dt":"13:16","nakshatra":"टि"},{"dt":"18:58","nakshatra":"टु"},{"dt":"24:38","nakshatra":"टे"},{"dt":"30:18","nakshatra":"टो"}]}},{"quarter":2,"week":42,"day":4,"date":29,"ad":"2020-10-15","bs":"29.06.2077","tithi":12,"nsYear":1140,"nsMonth":25,"chandrama":21.2,"events":[{"name":{"ne":"ग्रामीण महिला दिवस","en":"Rural Women's Day"},"jbo":"AD"}],"saits":[1],"panchanga":{"ad":"२०२०","saksambat":"१९४२","sambatsar":"प्रमादी","ayen":"दक्षिणायन","ritu":"शरद","nsyear":"११४०","nsmonth":null,"chandramasa":"अधिक आश्विन कृष्णपक्ष","tithi_name":"त्रयोदशी  ०६:२५  बजेदेखि चतुर्दशी , २८:१३  बजे उप्रान्त प्रतिपदा ","nakshatra":"उत्तरफाल्गुनी , १७:३६  बजे उप्रान्त हस्त ","yog":"ब्रह्म , १०:२६  बजे उप्रान्त ऐन्द्र ","karan":"वणिज  ०६:२५  बजेदेखि भद्रा , १७:२०  बजे उप्रान्त किंस्तुघ्न ","anandiyog":"मातंग","chandrarashi":"कन्या","sunrise":"०६:०४","sunset":"१७:३३","dinman":"२८।४१","parba":"अनलाचह्रे पूजा।","surya":"५:२७:२२:५६","chandra":"५:०३:११:४७","mangal":"११:१५:४३:१३","budha":"६:०७:५५:१६","brihaspati":"८:२६:०७:०९","sukra":"४:२१:१२:५६","sani":"८:२८:०६:१३","rahu":"१:२८:०८:४९","kranti":"द. ८:३१","belantar":"(–) १५:०७","birthname":[{"dt":"6:18","nakshatra":"टो"},{"dt":"11:57","nakshatra":"पा"},{"dt":"17:36","nakshatra":"पि"},{"dt":"23:13","nakshatra":"पु"},{"dt":"28:50","nakshatra":"ष"}]}},{"quarter":2,"week":42,"day":5,"date":30,"ad":"2020-10-16","bs":"30.06.2077","tithi":29,"nsYear":1140,"nsMonth":25,"chandrama":21.2,"events":[{"name":{"ne":"विश्व खाद्य दिवस","en":"World Food Day"},"jbo":"AD"}],"saits":[],"panchanga":{"ad":"२०२०","saksambat":"१९४२","sambatsar":"प्रमादी","ayen":"दक्षिणायन","ritu":"शरद","nsyear":"११४०","nsmonth":null,"chandramasa":"अधिक आश्विन कृष्णपक्ष","tithi_name":"औंसी , २५:५३  बजे उप्रान्त प्रतिपदा ","nakshatra":"हस्त , १६:०३  बजे उप्रान्त चित्रा ","yog":"ऐन्द्र  ०७:२९  बजेदेखि वैधृति , २८:२४  बजे उप्रान्त प्रीति ","karan":"चतुष्पद  १५:०४  बजेदेखि नाग , २५:५३  बजे उप्रान्त वालव ","anandiyog":"अमृत","chandrarashi":"कन्या","sunrise":"०६:०५","sunset":"१७:३२","dinman":"२८।३७","parba":"दर्शश्राद्ध। हलो तथा निशि बार्ने औंशी। अधिकमास समाप्ति। अपूपदान समाप्ति। मत्स्यनारायण मेला समापन। आश्विन मसान्त।","surya":"५:२८:२२:३५","chandra":"५:१७:२४:१८","mangal":"११:१५:३१:२४","budha":"६:०७:०८:५१","brihaspati":"८:२६:१२:५६","sukra":"४:२२:२४:२५","sani":"८:२८:०८:१४","rahu":"१:२८:०५:३८","kranti":"द. ८:५४","belantar":"(–) १५:२०","birthname":[{"dt":"10:27","nakshatra":"ण"},{"dt":"16:03","nakshatra":"ठ"},{"dt":"21:38","nakshatra":"पे"},{"dt":"27:14","nakshatra":"पो"},{"dt":"32:49","nakshatra":"रा"}]}}]